shinytext/__init__.py
shinytext/cleandata.py
shinytext/cleantext.py
shinytext/utils/chats.py
shinytext/utils/emoticons.py
shinytext/utils/spacy_loader.py
shinytext-0.0.3.dist-info/LICENSE
shinytext-0.0.3.dist-info/METADATA
shinytext-0.0.3.dist-info/WHEEL
shinytext-0.0.3.dist-info/top_level.txt
shinytext-0.0.3.dist-info/RECORD
