Metadata-Version: 2.1
Name: shinytext
Version: 0.0.3
Summary: A small text processing package
Author-email: Retin P Kumar <retinpkumar@gmail.com>
Project-URL: Homepage, https://github.com/Retinpkumar/ShinyText
Project-URL: Bug Tracker, https://github.com/Retinpkumar/ShinyText/issues
Classifier: Programming Language :: Python :: 3
Classifier: License :: OSI Approved :: MIT License
Classifier: Operating System :: OS Independent
Requires-Python: >=3.10
License-File: LICENSE
Requires-Dist: nltk
Requires-Dist: pyspellchecker
Requires-Dist: pandas
Requires-Dist: spacy
